lminapi/__init__.py
lminapi/lminapi.py
lminapi/utils/__init__.py
lminapi/utils/comfunc.py
lminapi/utils/params_to_dict.py
lminapi/utils/params_verify.py
lminapi/utils/return_code.py
lminapi-0.0.3.dist-info/LICENSE
lminapi-0.0.3.dist-info/METADATA
lminapi-0.0.3.dist-info/WHEEL
lminapi-0.0.3.dist-info/top_level.txt
lminapi-0.0.3.dist-info/RECORD
