Metadata-Version: 2.1
Name: lminapi
Version: 0.0.3
Summary: 基于django 和django rest framework整合简化drf APIView视图类常用方法, 简化传入参数已验证方法
Home-page: https://github.com/lxb0323/lminapi
Author: bing0323
Author-email: ltjlxb@163.com
License: MIT
Keywords: APIView,Validator,api
Platform: any
Classifier: Programming Language :: Python
Classifier: Programming Language :: Python :: 3
Classifier: Programming Language :: Python :: 3.4
Classifier: Programming Language :: Python :: 3.5
Classifier: Programming Language :: Python :: 3.6
Classifier: Programming Language :: Python :: 3.7
Classifier: Programming Language :: Python :: 3.8
Classifier: Programming Language :: Python :: 3.9
Requires-Dist: django (>=2.0.5)
Requires-Dist: djangorestframework (>=3.11.0)
